aleksis/apps/csv_import/__init__.py
aleksis/apps/csv_import/admin.py
aleksis/apps/csv_import/apps.py
aleksis/apps/csv_import/default_templates.py
aleksis/apps/csv_import/default_templates.yaml
aleksis/apps/csv_import/field_types.py
aleksis/apps/csv_import/forms.py
aleksis/apps/csv_import/frontend/components/CSVImport.vue
aleksis/apps/csv_import/frontend/components/ImportTemplateField.vue
aleksis/apps/csv_import/frontend/components/import.graphql
aleksis/apps/csv_import/frontend/components/importTemplates.graphql
aleksis/apps/csv_import/frontend/index.js
aleksis/apps/csv_import/frontend/messages/ar.json
aleksis/apps/csv_import/frontend/messages/de.json
aleksis/apps/csv_import/frontend/messages/en.json
aleksis/apps/csv_import/frontend/messages/fr.json
aleksis/apps/csv_import/frontend/messages/la.json
aleksis/apps/csv_import/frontend/messages/nb_NO.json
aleksis/apps/csv_import/frontend/messages/ru.json
aleksis/apps/csv_import/frontend/messages/tr.json
aleksis/apps/csv_import/frontend/messages/uk.json
aleksis/apps/csv_import/frontend/mixins/additionalParamsMixin.js
aleksis/apps/csv_import/locale/ar/LC_MESSAGES/django.mo
aleksis/apps/csv_import/locale/ar/LC_MESSAGES/django.po
aleksis/apps/csv_import/locale/de_DE/LC_MESSAGES/django.mo
aleksis/apps/csv_import/locale/de_DE/LC_MESSAGES/django.po
aleksis/apps/csv_import/locale/fr/LC_MESSAGES/django.mo
aleksis/apps/csv_import/locale/fr/LC_MESSAGES/django.po
aleksis/apps/csv_import/locale/la/LC_MESSAGES/django.mo
aleksis/apps/csv_import/locale/la/LC_MESSAGES/django.po
aleksis/apps/csv_import/locale/nb_NO/LC_MESSAGES/django.mo
aleksis/apps/csv_import/locale/nb_NO/LC_MESSAGES/django.po
aleksis/apps/csv_import/locale/ru/LC_MESSAGES/django.mo
aleksis/apps/csv_import/locale/ru/LC_MESSAGES/django.po
aleksis/apps/csv_import/locale/tr_TR/LC_MESSAGES/django.mo
aleksis/apps/csv_import/locale/tr_TR/LC_MESSAGES/django.po
aleksis/apps/csv_import/locale/uk/LC_MESSAGES/django.mo
aleksis/apps/csv_import/locale/uk/LC_MESSAGES/django.po
aleksis_app_csvimport-4.0.0.post1.dist-info/LICENCE.rst
aleksis_app_csvimport-4.0.0.post1.dist-info/METADATA
aleksis_app_csvimport-4.0.0.post1.dist-info/WHEEL
aleksis_app_csvimport-4.0.0.post1.dist-info/entry_points.txt
aleksis_app_csvimport-4.0.0.post1.dist-info/RECORD
