Metadata-Version: 2.3
Name: AlekSIS-App-CSVImport
Version: 4.0.0.post1
Summary: AlekSIS (School Information System) — App for CSV import
License: EUPL-1.2-or-later
Author: Dominik George
Author-email: dominik.george@teckids.org
Maintainer: Jonathan Weth
Maintainer-email: jonathan.weth@teckids.org
Requires-Python: >=3.10,<4.0
Classifier: Development Status :: 5 - Production/Stable
Classifier: Environment :: Web Environment
Classifier: Intended Audience :: Education
Classifier: License :: Other/Proprietary License
Classifier: Programming Language :: Python :: 3
Classifier: Programming Language :: Python :: 3.10
Classifier: Programming Language :: Python :: 3.11
Classifier: Programming Language :: Python :: 3.12
Classifier: Programming Language :: Python :: 3.13
Classifier: Topic :: Education
Requires-Dist: aleksis-app-chronos (>=4.0.1,<5.0.0)
Requires-Dist: aleksis-app-cursus (>=1.0.1,<2.0.0)
Requires-Dist: aleksis-app-lesrooster (>=1.0.1,<2.0.0)
Requires-Dist: aleksis-core (>=4.0.2,<5.0.0)
Requires-Dist: chardet (>=5.0.0,<6.0.0)
Requires-Dist: dateparser (>=1.0.0,<2.0.0)
Requires-Dist: numpy (<2.3.0)
Requires-Dist: pandas (>=2.0.0,<3.0.0)
Requires-Dist: phonenumbers (>=8.0.0,<9.0.0)
Requires-Dist: ruamel.yaml (>=0.18.0,<0.19.0)
Requires-Dist: tqdm (>=4.62.3,<5.0.0)
Project-URL: Documentation, https://aleksis.edugit.io/AlekSIS/docs/html/
Project-URL: Homepage, https://aleksis.org
Project-URL: Repository, https://edugit.org/AlekSIS/Onboarding/AlekSIS-App-CSVImport
